Workbook

Sheet COMPRAS 2025
O1: CÓDIGO: | P1: PE-LC-01
I2: LIBRO DE COMPRAS 2025 | O2: VERSIÓN: | P2: 1
O3: FECHA: | P3: 45665
A5: ALERTA | B5: DOCUMENTO | C5: EMPRESA | D5: FECHA VENCIMIENTO | E5: FECHA EMISION | F5: N° MES | G5: N° FOLIO | H5: RUT | I5: RAZON SOCIAL | J5: NETO | K5: IVA | L5: MONTO TOTAL | M5: ESTADO | N5: METODO DE PAGO | O5: CENTRO DE COSTOS | P5: DESCRIPCION
A6: ='COMPRAS 2025'!$D6-TODAY() -> -388 | B6: FACTURA | C6: PET EXOTIC LTDA | D6: 45660 | E6: 45660 | F6: =MONTH('COMPRAS 2025'!$E6) -> 1 | G6: 1908941 | H6: 83382700-6 | I6: COMERCIAL ECCSA SA | J6: 327723 | K6: 62267 | L6: ='COMPRAS 2025'!$J6+'COMPRAS 2025'!$K6 -> 389990 | M6: PAGADO | N6: DEBITO | O6: Mercancia - Proveedores
A7: ='COMPRAS 2025'!$D7-TODAY() -> -354 | B7: FACTURA | C7: PET EXOTIC LTDA | D7: 45694 | E7: 45664 | F7: =MONTH('COMPRAS 2025'!$E7) -> 1 | G7: 380775 | H7: 76080982-9 | I7: DIPROVET DISTRIBUIDORA DE PRODUCTOS VETERINARIOS SPA | J7: 100853 | K7: 19162 | L7: ='COMPRAS 2025'!$J7+'COMPRAS 2025'!$K7 -> 120015 | M7: PAGADO | N7: CREDITO | O7: Mercancia - Proveedores
A8: ='COMPRAS 2025'!$D8-TODAY() -> -354 | B8: FACTURA | C8: PET EXOTIC LTDA | D8: 45694 | E8: 45664 | F8: =MONTH('COMPRAS 2025'!$E8) -> 1 | G8: 380776 | H8: 76080982-9 | I8: DIPROVET DISTRIBUIDORA DE PRODUCTOS VETERINARIOS SPA | J8: 132790 | K8: 25230 | L8: ='COMPRAS 2025'!$J8+'COMPRAS 2025'!$K8 -> 158020 | M8: PAGADO | N8: CREDITO | O8: Mercancia - Proveedores
A9: ='COMPRAS 2025'!$D9-TODAY() -> -385 | B9: FACTURA | C9: PET EXOTIC LTDA | D9: 45663 | E9: 45663 | F9: =MONTH('COMPRAS 2025'!$E9) -> 1 | G9: 5483933 | H9: 76979850-1 | I9: FABRICA DE BANDEJAS LIMITADA | J9: 9229 | K9: 1754 | L9: ='COMPRAS 2025'!$J9+'COMPRAS 2025'!$K9 -> 10983 | M9: PAGADO | N9: DEBITO | O9: Mercancia - Proveedores
A10: ='COMPRAS 2025'!$D10-TODAY() -> -389 | B10: FACTURA | C10: PET EXOTIC LTDA | D10: 45659 | E10: 45659 | F10: =MONTH('COMPRAS 2025'!$E10) -> 1 | G10: 216729 | H10: 9538683-0 | I10: CLAUDIO ARANCIBIA DONOSO | J10: 4370 | K10: 830 | L10: ='COMPRAS 2025'!$J10+'COMPRAS 2025'!$K10 -> 5200 | M10: PAGADO | N10: EFECTIVO | O10: Mercancia - Proveedores
A11: ='COMPRAS 2025'!$D11-TODAY() -> -389 | B11: FACTURA | C11: PET EXOTIC LTDA | D11: 45659 | E11: 45659 | F11: =MONTH('COMPRAS 2025'!$E11) -> 1 | G11: 16365 | H11: 16774813-9 | I11: JOSE IGNACIO MORENO URRA | J11: 5882 | K11: 1118 | L11: ='COMPRAS 2025'!$J11+'COMPRAS 2025'!$K11 -> 7000 | M11: PAGADO | N11: DEBITO | O11: Mercancia - Proveedores
A12: ='COMPRAS 2025'!$D12-TODAY() -> -370 | B12: FACTURA | C12: PET EXOTIC LTDA | D12: 45678 | E12: 45678 | F12: =MONTH('COMPRAS 2025'!$E12) -> 1 | G12: 5505318 | H12: 76979850-1 | I12: FABRICA DE BANDEJAS LIMITADA | J12: 16700 | K12: 3173 | L12: ='COMPRAS 2025'!$J12+'COMPRAS 2025'!$K12 -> 19873 | M12: PAGADO | N12: DEBITO | O12: Mercancia - Proveedores
A13: ='COMPRAS 2025'!$D13-TODAY() -> -370 | B13: BOLETA | C13: PET EXOTIC LTDA | D13: 45678 | E13: 45678 | F13: =MONTH('COMPRAS 2025'!$E13) -> 1 | G13: 9683105 | H13: 76979850-1 | I13: FABRICA DE BANDEJAS LIMITADA | J13: 3872 | K13: 736 | L13: ='COMPRAS 2025'!$J13+'COMPRAS 2025'!$K13 -> 4608 | M13: PAGADO | N13: DEBITO | O13: Mercancia - Proveedores
A14: ='COMPRAS 2025'!$D14-TODAY() -> -338 | B14: FACTURA | C14: PET EXOTIC LTDA | D14: 45710 | E14: 45680 | F14: =MONTH('COMPRAS 2025'!$E14) -> 1 | G14: 382918 | H14: 76080982-9 | I14: DIPROVET DISTRIBUIDORA DE PRODUCTOS VETERINARIOS SPA | J14: 72500 | K14: 13775 | L14: ='COMPRAS 2025'!$J14+'COMPRAS 2025'!$K14 -> 86275 | M14: PAGADO | N14: CREDITO | O14: Mercancia - Proveedores
A15: ='COMPRAS 2025'!$D15-TODAY() -> -338 | B15: FACTURA | C15: PET EXOTIC LTDA | D15: 45710 | E15: 45680 | F15: =MONTH('COMPRAS 2025'!$E15) -> 1 | G15: 382917 | H15: 76080982-9 | I15: DIPROVET DISTRIBUIDORA DE PRODUCTOS VETERINARIOS SPA | J15: 66460 | K15: 12627 | L15: ='COMPRAS 2025'!$J15+'COMPRAS 2025'!$K15 -> 79087 | M15: PAGADO | N15: CREDITO | O15: Mercancia - Proveedores
A16: ='COMPRAS 2025'!$D16-TODAY() -> -363 | B16: FACTURA | C16: PET EXOTIC LTDA | D16: 45685 | E16: 45685 | F16: =MONTH('COMPRAS 2025'!$E16) -> 1 | G16: 2796129 | H16: 80478200-1 | I16: ILOP SA | J16: 9479 | K16: 1801 | L16: ='COMPRAS 2025'!$J16+'COMPRAS 2025'!$K16 -> 11280 | M16: PAGADO | N16: DEBITO | O16: Mercancia - Proveedores
A17: ='COMPRAS 2025'!$D17-TODAY() -> -320 | B17: FACTURA | C17: PET EXOTIC LTDA | D17: 45728 | E17: 45698 | F17: =MONTH('COMPRAS 2025'!$E17) -> 2 | G17: 385112 | H17: 76080982-9 | I17: DIPROVET DISTRIBUIDORA DE PRODUCTOS VETERINARIOS SPA | J17: 58850 | K17: 11182 | L17: ='COMPRAS 2025'!$J17+'COMPRAS 2025'!$K17 -> 70032 | M17: PAGADO | N17: CREDITO | O17: Mercancia - Proveedores
... A50: ='COMPRAS 2025'!$D50-TODAY() -> -286 | B50: FACTURA | C50: PET EXOTIC LTDA | D50: 45762 | E50: 45762 | F50: =MONTH('COMPRAS 2025'!$E50) -> 4 | G50: 24004864 | H50: 81201000-K | I50: CENCOSUD RETAIL SA | J50: 12111 | K50: 2301 | L50: ='COMPRAS 2025'!$J50+'COMPRAS 2025'!$K50 -> 14412 | M50: PAGADO | N50: DEBITO | O50: Mercancia - Proveedores
A51: ='COMPRAS 2025'!$D51-TODAY() -> -283 | B51: FACTURA | C51: PET EXOTIC LTDA | D51: 45765 | E51: 45765 | F51: =MONTH('COMPRAS 2025'!$E51) -> 4 | G51: 57266614 | H51: 76134946-5 | I51: SUPERMERCADO LIDER | J51: 16729 | K51: =3179+182 -> 3361 | L51: ='COMPRAS 2025'!$J51+'COMPRAS 2025'!$K51 -> 20090 | M51: PAGADO | N51: DEBITO | O51: Mercancia - Proveedores
A52: ='COMPRAS 2025'!$D52-TODAY() -> -280 | B52: FACTURA | C52: PET EXOTIC LTDA | D52: 45768 | E52: 45768 | F52: =MONTH('COMPRAS 2025'!$E52) -> 4 | G52: 5676738 | H52: 76979850-1 | I52: FABRICA DE BANDEJAS LIMITADA | J52: 7631 | K52: 1450 | L52: ='COMPRAS 2025'!$J52+'COMPRAS 2025'!$K52 -> 9081 | M52: PAGADO | N52: DEBITO | O52: Mercancia - Proveedores
A53: ='COMPRAS 2025'!$D53-TODAY() -> -255 | B53: FACTURA | C53: PET EXOTIC LTDA | D53: 45793 | E53: 45763 | F53: =MONTH('COMPRAS 2025'!$E53) -> 4 | G53: 115157 | H53: 76218200-9 | I53: DYKONOS CIA LIMITADA | J53: 118429 | K53: 22502 | L53: ='COMPRAS 2025'!$J53+'COMPRAS 2025'!$K53 -> 140931 | M53: PAGADO | N53: CREDITO | O53: Mercancia - Proveedores
A54: ='COMPRAS 2025'!$D54-TODAY() -> -255 | B54: FACTURA | C54: PET EXOTIC LTDA | D54: 45793 | E54: 45763 | F54: =MONTH('COMPRAS 2025'!$E54) -> 4 | G54: 115172 | H54: 76218200-9 | I54: DYKONOS CIA LIMITADA | J54: 13402 | K54: 2546 | L54: ='COMPRAS 2025'!$J54+'COMPRAS 2025'!$K54 -> 15948 | M54: PAGADO | N54: CREDITO | O54: Mercancia - Proveedores
A55: ='COMPRAS 2025'!$D55-TODAY() -> -248 | B55: FACTURA | C55: PET EXOTIC LTDA | D55: 45800 | E55: 45770 | F55: =MONTH('COMPRAS 2025'!$E55) -> 4 | G55: 394531 | H55: 76080982-9 | I55: DIPROVET DISTRIBUIDORA DE PRODUCTOS VETERINARIOS SPA | J55: 24980 | K55: 4746 | L55: ='COMPRAS 2025'!$J55+'COMPRAS 2025'!$K55 -> 29726 | M55: PAGADO | N55: CREDITO | O55: Mercancia - Proveedores
A56: ='COMPRAS 2025'!$D56-TODAY() -> -248 | B56: FACTURA | C56: PET EXOTIC LTDA | D56: 45800 | E56: 45770 | F56: =MONTH('COMPRAS 2025'!$E56) -> 4 | G56: 394530 | H56: 76080982-9 | I56: DIPROVET DISTRIBUIDORA DE PRODUCTOS VETERINARIOS SPA | J56: 112840 | K56: 21440 | L56: ='COMPRAS 2025'!$J56+'COMPRAS 2025'!$K56 -> 134280 | M56: PAGADO | N56: CREDITO | O56: Mercancia - Proveedores
A57: ='COMPRAS 2025'!$D57-TODAY() -> -248 | B57: FACTURA | C57: PET EXOTIC LTDA | D57: 45800 | E57: 45770 | F57: =MONTH('COMPRAS 2025'!$E57) -> 4 | G57: 394529 | H57: 76080982-9 | I57: DIPROVET DISTRIBUIDORA DE PRODUCTOS VETERINARIOS SPA | J57: 56660 | K57: 10765 | L57: ='COMPRAS 2025'!$J57+'COMPRAS 2025'!$K57 -> 67425 | M57: PAGADO | N57: CREDITO | O57: Mercancia - Proveedores
A58: ='COMPRAS 2025'!$D58-TODAY() -> -246 | B58: FACTURA | C58: PET EXOTIC LTDA | D58: 45802 | E58: 45772 | F58: =MONTH('COMPRAS 2025'!$E58) -> 4 | G58: 11136 | H58: 76046685-9 | I58: DATAMEDICA S.P.A | J58: 90000 | K58: 17100 | L58: ='COMPRAS 2025'!$J58+'COMPRAS 2025'!$K58 -> 107100 | M58: PAGADO | N58: CREDITO | O58: Mercancia - Proveedores
A59: ='COMPRAS 2025'!$D59-TODAY() -> -241 | B59: FACTURA | C59: PET EXOTIC SPA | D59: 45807 | E59: 45777 | F59: =MONTH('COMPRAS 2025'!$E59) -> 4 | G59: 101182 | H59: 76936850-7 | I59: ANIMAL CARE - ACWS S.A | J59: 89716 | K59: 17046 | L59: ='COMPRAS 2025'!$J59+'COMPRAS 2025'!$K59 -> 106762 | M59: PAGADO | N59: CREDITO | O59: Mercancia - Proveedores
A60: ='COMPRAS 2025'!$D60-TODAY() -> -236 | B60: FACTURA | C60: PET EXOTIC LTDA | D60: 45812 | E60: 45782 | F60: =MONTH('COMPRAS 2025'!$E60) -> 5 | G60: 115481 | H60: 76218200-9 | I60: DYKONOS CIA LIMITADA | J60: 130769 | K60: 24846 | L60: ='COMPRAS 2025'!$J60+'COMPRAS 2025'!$K60 -> 155615 | M60: PAGADO | N60: CREDITO | O60: Mercancia - Proveedores
A61: ='COMPRAS 2025'!$D61-TODAY() -> -236 | B61: NOTA DE CREDITO | C61: PET EXOTIC LTDA | D61: 45812 | E61: 45783 | F61: =MONTH('COMPRAS 2025'!$E61) -> 5 | G61: 10677 | H61: 76218200-9 | I61: DYKONOS CIA LIMITADA | J61: 10500 | K61: 1995 | L61: =-'COMPRAS 2025'!$K61 - 'COMPRAS 2025'!$J61 -> -12495 | M61: PAGADO | N61: CREDITO | O61: Mercancia - Proveedores
A62: ='COMPRAS 2025'!$D62-TODAY() -> -235 | B62: FACTURA | C62: PET EXOTIC LTDA | D62: 45813 | E62: 45783 | F62: =MONTH('COMPRAS 2025'!$E62) -> 5 | G62: 115482 | H62: 76218200-9 | I62: DYKONOS CIA LIMITADA | J62: 14995 | K62: 2849 | L62: ='COMPRAS 2025'!$K62 + 'COMPRAS 2025'!$J62 -> 17844 | M62: PAGADO | N62: CREDITO | O62: Mercancia - Proveedores
A63: ='COMPRAS 2025'!$D63-TODAY() -> -226 | B63: FACTURA | C63: PET EXOTIC LTDA | D63: 45822 | E63: 45792 | F63: =MONTH('COMPRAS 2025'!$E63) -> 5 | G63: 397334 | H63: 76080982-9 | I63: DIPROVET DISTRIBUIDORA DE PRODUCTOS VETERINARIOS SPA | J63: 20560 | K63: 3906 | L63: ='COMPRAS 2025'!$J63+'COMPRAS 2025'!$K63 -> 24466 | M63: PAGADO | N63: CREDITO | O63: Mercancia - Proveedores
A64: ='COMPRAS 2025'!$D64-TODAY() -> -226 | B64: FACTURA | C64: PET EXOTIC LTDA | D64: 45822 | E64: 45792 | F64: =MONTH('COMPRAS 2025'!$E64) -> 5 | G64: 397333 | H64: 76080982-9 | I64: DIPROVET DISTRIBUIDORA DE PRODUCTOS VETERINARIOS SPA | J64: 80500 | K64: 15295 | L64: ='COMPRAS 2025'!$J64+'COMPRAS 2025'!$K64 -> 95795 | M64: PAGADO | N64: CREDITO | O64: Mercancia - Proveedores
A65: ='COMPRAS 2025'!$D65-TODAY() -> -226 | B65: FACTURA | C65: PET EXOTIC LTDA | D65: 45822 | E65: 45792 | F65: =MONTH('COMPRAS 2025'!$E65) -> 5 | G65: 115704 | H65: 76218200-9 | I65: DYKONOS CIA LIMITADA | J65: 7120 | K65: 1353 | L65: ='COMPRAS 2025'!$J65+'COMPRAS 2025'!$K65 -> 8473 | M65: PAGADO | N65: CREDITO | O65: Mercancia - Proveedores
A66: ='COMPRAS 2025'!$D66-TODAY() -> -225 | B66: BOLETA | C66: RONALD RENE MIGUEL DIAZ ROJAS | D66: 45823 | E66: 45792 | F66: =MONTH('COMPRAS 2025'!$E66) -> 5 | G66: 14914 | H66: 76218200-9 | I66: DYKONOS CIA LIMITADA | J66: 44960 | K66: 8542 | L66: ='COMPRAS 2025'!$J66+'COMPRAS 2025'!$K66 -> 53502 | M66: PAGADO | N66: CREDITO | O66: Mercancia - Proveedores
A67: ='COMPRAS 2025'!$D67-TODAY() -> -222 | B67: FACTURA | C67: PET EXOTIC LTDA | D67: 45826 | E67: 45796 | F67: =MONTH('COMPRAS 2025'!$E67) -> 5 | G67: 397616 | H67: 76080982-9 | I67: DIPROVET DISTRIBUIDORA DE PRODUCTOS VETERINARIOS SPA | J67: 11980 | K67: 2276 | L67: ='COMPRAS 2025'!$J67+'COMPRAS 2025'!$K67 -> 14256 | M67: PAGADO | N67: CREDITO | O67: Mercancia - Proveedores
A68: ='COMPRAS 2025'!$D68-TODAY() -> -222 | B68: FACTURA | C68: PET EXOTIC LTDA | D68: 45826 | E68: 45796 | F68: =MONTH('COMPRAS 2025'!$E68) -> 5 | G68: 397617 | H68: 76080982-9 | I68: DIPROVET DISTRIBUIDORA DE PRODUCTOS VETERINARIOS SPA | J68: 12270 | K68: 2331 | L68: ='COMPRAS 2025'!$J68+'COMPRAS 2025'!$K68 -> 14601 | M68: PAGADO | N68: CREDITO | O68: Mercancia - Proveedores
A69: ='COMPRAS 2025'!$D69-TODAY() -> -222 | B69: FACTURA | C69: PET EXOTIC LTDA | D69: 45826 | E69: 45796 | F69: =MONTH('COMPRAS 2025'!$E69) -> 5 | G69: 397615 | H69: 76080982-9 | I69: DIPROVET DISTRIBUIDORA DE PRODUCTOS VETERINARIOS SPA | J69: 102710 | K69: 19515 | L69: ='COMPRAS 2025'!$J69+'COMPRAS 2025'!$K69 -> 122225 | M69: PAGADO | N69: CREDITO | O69: Mercancia - Proveedores
A70: ='COMPRAS 2025'!$D70-TODAY() -> -218 | B70: FACTURA | C70: PET EXOTIC LTDA | D70: 45830 | E70: 45800 | F70: =MONTH('COMPRAS 2025'!$E70) -> 5 | G70: 11230 | H70: 76046685-9 | I70: DATAMEDICA S.P.A | J70: 90000 | K70: 17100 | L70: ='COMPRAS 2025'!$J70+'COMPRAS 2025'!$K70 -> 107100 | M70: PAGADO | N70: CREDITO | O70: Mercancia - Proveedores
A71: ='COMPRAS 2025'!$D71-TODAY() -> -238 | B71: FACTURA | C71: PET EXOTIC LTDA | D71: 45810 | E71: 45810 | F71: =MONTH('COMPRAS 2025'!$E71) -> 6 | G71: 3615 | H71: 762510138 | I71: GRANJA AGRICOLA Y GANADERA LAURA ROSA LIMITADA | J71: 22681 | K71: 4309 | L71: ='COMPRAS 2025'!$J71+'COMPRAS 2025'!$K71 -> 26990 | M71: PAGADO | N71: DEBITO | O71: Mercancia - Proveedores
A72: ='COMPRAS 2025'!$D72-TODAY() -> -205 | B72: FACTURA | C72: PET EXOTIC LTDA | D72: 45843 | E72: 45813 | F72: =MONTH('COMPRAS 2025'!$E72) -> 6 | G72: 399796 | H72: 76080982-9 | I72: DIPROVET DISTRIBUIDORA DE PRODUCTOS VETERINARIOS SPA | J72: 142630 | K72: 27100 | L72: ='COMPRAS 2025'!$J72+'COMPRAS 2025'!$K72 -> 169730 | M72: PAGADO | N72: CREDITO | O72: Mercancia - Proveedores
A73: ='COMPRAS 2025'!$D73-TODAY() -> -205 | B73: FACTURA | C73: PET EXOTIC LTDA | D73: 45843 | E73: 45813 | F73: =MONTH('COMPRAS 2025'!$E73) -> 6 | G73: 399798 | H73: 76080982-9 | I73: DIPROVET DISTRIBUIDORA DE PRODUCTOS VETERINARIOS SPA | J73: 86110 | K73: 16361 | L73: ='COMPRAS 2025'!$J73+'COMPRAS 2025'!$K73 -> 102471 | M73: PAGADO | N73: CREDITO | O73: Mercancia - Proveedores
A74: ='COMPRAS 2025'!$D74-TODAY() -> -198 | B74: FACTURA | C74: PET EXOTIC LTDA | D74: 45850 | E74: 45820 | F74: =MONTH('COMPRAS 2025'!$E74) -> 6 | G74: 400612 | H74: 76080982-9 | I74: DIPROVET DISTRIBUIDORA DE PRODUCTOS VETERINARIOS SPA | J74: 51470 | K74: 9779 | L74: ='COMPRAS 2025'!$J74+'COMPRAS 2025'!$K74 -> 61249 | M74: PAGADO | N74: CREDITO | O74: Mercancia - Proveedores
A75: ='COMPRAS 2025'!$D75-TODAY() -> -198 | B75: FACTURA | C75: PET EXOTIC LTDA | D75: 45850 | E75: 45820 | F75: =MONTH('COMPRAS 2025'!$E75) -> 6 | G75: 400613 | H75: 76080982-9 | I75: DIPROVET DISTRIBUIDORA DE PRODUCTOS VETERINARIOS SPA | J75: 29990 | K75: 5698 | L75: ='COMPRAS 2025'!$J75+'COMPRAS 2025'!$K75 -> 35688 | M75: PAGADO | N75: CREDITO | O75: Mercancia - Proveedores
A76: ='COMPRAS 2025'!$D76-TODAY() -> -198 | B76: FACTURA | C76: PET EXOTIC LTDA | D76: 45850 | E76: 45820 | F76: =MONTH('COMPRAS 2025'!$E76) -> 6 | G76: 400614 | H76: 76080982-9 | I76: DIPROVET DISTRIBUIDORA DE PRODUCTOS VETERINARIOS SPA | J76: 55350 | K76: 10517 | L76: ='COMPRAS 2025'!$J76+'COMPRAS 2025'!$K76 -> 65867 | M76: PAGADO | N76: CREDITO | O76: Mercancia - Proveedores
A77: ='COMPRAS 2025'!$D77-TODAY() -> -187 | B77: FACTURA | C77: PET EXOTIC LTDA | D77: 45861 | E77: 45831 | F77: =MONTH('COMPRAS 2025'!$E77) -> 6 | G77: 11401 | H77: 76046685-9 | I77: DATAMEDICA S.P.A. | J77: 90000 | K77: 17100 | L77: ='COMPRAS 2025'!$J77+'COMPRAS 2025'!$K77 -> 107100 | M77: PAGADO | N77: CREDITO | O77: Mercancia - Proveedores
A78: ='COMPRAS 2025'!$D78-TODAY() -> -209 | B78: FACTURA | C78: PET EXOTIC LTDA | D78: 45839 | E78: 45839 | F78: =MONTH('COMPRAS 2025'!$E78) -> 7 | G78: 46351 | H78: 76839842-9 | I78: COMERCIALIZADORA MGASES SPA | J78: 39220 | K78: 7452 | L78: ='COMPRAS 2025'!$J78+'COMPRAS 2025'!$K78 -> 46672 | M78: PAGADO | N78: TRASFERENCIA | O78: Mercancia - Proveedores
A79: ='COMPRAS 2025'!$D79-TODAY() -> -176 | B79: FACTURA | C79: PET EXOTIC LTDA | D79: 45872 | E79: 45842 | F79: =MONTH('COMPRAS 2025'!$E79) -> 7 | G79: 403062 | H79: 76080982-9 | I79: DIPROVET DISTRIBUIDORA DE PRODUCTOS VETERINARIOS SPA | J79: 135435 | K79: 25733 | L79: ='COMPRAS 2025'!$J79+'COMPRAS 2025'!$K79 -> 161168 | M79: PAGADO | N79: CREDITO | O79: Mercancia - Proveedores
A80: ='COMPRAS 2025'!$D80-TODAY() -> -176 | B80: FACTURA | C80: PET EXOTIC LTDA | D80: 45872 | E80: 45842 | F80: =MONTH('COMPRAS 2025'!$E80) -> 7 | G80: 403061 | H80: 76080982-9 | I80: DIPROVET DISTRIBUIDORA DE PRODUCTOS VETERINARIOS SPA | J80: 50060 | K80: 9511 | L80: ='COMPRAS 2025'!$J80+'COMPRAS 2025'!$K80 -> 59571 | M80: PAGADO | N80: CREDITO | O80: Mercancia - Proveedores
A81: ='COMPRAS 2025'!$D81-TODAY() -> -163 | B81: FACTURA | C81: PET EXOTIC LTDA | D81: 45885 | E81: 45855 | F81: =MONTH('COMPRAS 2025'!$E81) -> 7 | G81: 404430 | H81: 76080982-9 | I81: DIPROVET DISTRIBUIDORA DE PRODUCTOS VETERINARIOS SPA | J81: 58980 | K81: 11208 | L81: ='COMPRAS 2025'!$J81+'COMPRAS 2025'!$K81 -> 70188 | M81: PAGADO | N81: CREDITO | O81: Mercancia - Proveedores
A82: ='COMPRAS 2025'!$D82-TODAY() -> -163 | B82: FACTURA | C82: PET EXOTIC LTDA | D82: 45885 | E82: 45855 | F82: =MONTH('COMPRAS 2025'!$E82) -> 7 | G82: 404431 | H82: 76080982-9 | I82: DIPROVET DISTRIBUIDORA DE PRODUCTOS VETERINARIOS SPA | J82: 51980 | K82: 9876 | L82: ='COMPRAS 2025'!$J82+'COMPRAS 2025'!$K82 -> 61856 | M82: PAGADO | N82: CREDITO | O82: Mercancia - Proveedores
A83: ='COMPRAS 2025'!$D83-TODAY() -> -163 | B83: FACTURA | C83: PET EXOTIC LTDA | D83: 45885 | E83: 45855 | F83: =MONTH('COMPRAS 2025'!$E83) -> 7 | G83: 404432 | H83: 76080982-9 | I83: DIPROVET DISTRIBUIDORA DE PRODUCTOS VETERINARIOS SPA | J83: 62820 | K83: 11936 | L83: ='COMPRAS 2025'!$J83+'COMPRAS 2025'!$K83 -> 74756 | M83: PAGADO | N83: CREDITO | O83: Mercancia - Proveedores
... A85: ='COMPRAS 2025'!$D85-TODAY() -> -157 | B85: FACTURA | C85: PET EXOTIC SPA | D85: 45891 | E85: 45861 | F85: =MONTH('COMPRAS 2025'!$E85) -> 7 | G85: 103410 | H85: 76936850-7 | I85: ANIMAL CARE - ACWS S.A | J85: 229105 | K85: 43530 | L85: ='COMPRAS 2025'!$J85+'COMPRAS 2025'!$K85 -> 272635 | M85: PAGADO | N85: CREDITO | O85: Mercancia - Proveedores
A86: ='COMPRAS 2025'!$D86-TODAY() -> -157 | B86: FACTURA | C86: PET EXOTIC LTDA | D86: 45891 | E86: 45861 | F86: =MONTH('COMPRAS 2025'!$E86) -> 7 | G86: 11581 | H86: 760466859 | I86: DATAMEDICA S.P.A | J86: 90000 | K86: 17100 | L86: ='COMPRAS 2025'!$J86+'COMPRAS 2025'!$K86 -> 107100 | M86: PAGADO | N86: CREDITO | O86: Mercancia - Proveedores
A87: ='COMPRAS 2025'!$D87-TODAY() -> -209 | B87: FACTURA | C87: PET EXOTIC LTDA | D87: 45839 | E87: 45839 | F87: =MONTH('COMPRAS 2025'!$E87) -> 7 | G87: 231526 | H87: 9538683-0 | I87: CLAUDIO ARANCIBIA DONOSO | J87: 9836 | K87: 1868 | L87: ='COMPRAS 2025'!$J87+'COMPRAS 2025'!$K87 -> 11704 | M87: PAGADO | N87: DEBITO | O87: Mercancia - Proveedores
A88: ='COMPRAS 2025'!$D88-TODAY() -> -200 | B88: FACTURA | C88: PET EXOTIC LTDA | D88: 45848 | E88: 45848 | F88: =MONTH('COMPRAS 2025'!$E88) -> 7 | G88: 2916068 | H88: 60503000-9 | I88: EMPRESA CORREOS DE CHILE | J88: 6520 | K88: 0 | L88: ='COMPRAS 2025'!$J88+'COMPRAS 2025'!$K88 -> 6520 | M88: PAGADO | N88: EFECTIVO | O88: Mercancia - Proveedores
A89: ='COMPRAS 2025'!$D89-TODAY() -> -200 | B89: FACTURA | C89: PET EXOTIC LTDA | D89: 45848 | E89: 45848 | F89: =MONTH('COMPRAS 2025'!$E89) -> 7 | G89: 2916071 | H89: 60503000-9 | I89: EMPRESA CORREOS DE CHILE | J89: 2720 | K89: 0 | L89: ='COMPRAS 2025'!$J89+'COMPRAS 2025'!$K89 -> 2720 | M89: PAGADO | N89: EFECTIVO | O89: Mercancia - Proveedores
A90: ='COMPRAS 2025'!$D90-TODAY() -> -170 | B90: FACTURA | C90: PET EXOTIC LTDA | D90: 45878 | E90: 45848 | F90: =MONTH('COMPRAS 2025'!$E90) -> 7 | G90: 403725 | H90: 76080982-9 | I90: DIPROVET DISTRIBUIDORA DE PRODUCTOS VETERINARIOS SPA | J90: 21990 | K90: 4178 | L90: ='COMPRAS 2025'!$J90+'COMPRAS 2025'!$K90 -> 26168 | M90: PAGADO | N90: CREDITO | O90: Mercancia - Proveedores
A91: ='COMPRAS 2025'!$D91-TODAY() -> -195 | B91: FACTURA | C91: PET EXOTIC LTDA | D91: 45853 | E91: 45853 | F91: =MONTH('COMPRAS 2025'!$E91) -> 7 | G91: 78471366 | H91: 76134946-5 | I91: SUPERMERCADO LIDER | J91: 16067 | K91: 3053 | L91: ='COMPRAS 2025'!$J91+'COMPRAS 2025'!$K91 -> 19120 | M91: PAGADO | N91: EFECTIVO | O91: Mercancia - Proveedores
A92: ='COMPRAS 2025'!$D92-TODAY() -> -188 | B92: FACTURA | C92: PET EXOTIC LTDA | D92: 45860 | E92: 45860 | F92: =MONTH('COMPRAS 2025'!$E92) -> 7 | G92: 21707 | H92: 76296220-9 | I92: COMERCIAL EXPRESS DEL PACIFICO LIMITADA | J92: 6966 | K92: 1324 | L92: ='COMPRAS 2025'!$J92+'COMPRAS 2025'!$K92 -> 8290 | M92: PAGADO | N92: EFECTIVO | O92: Mercancia - Proveedores
A93: ='COMPRAS 2025'!$D93-TODAY() -> -188 | B93: FACTURA | C93: PET EXOTIC LTDA | D93: 45860 | E93: 45860 | F93: =MONTH('COMPRAS 2025'!$E93) -> 7 | G93: 233197 | H93: 9538683-0 | I93: CLAUDIO ARANCIBIA DONOSO | J93: 11050 | K93: 2100 | L93: ='COMPRAS 2025'!$J93+'COMPRAS 2025'!$K93 -> 13150 | M93: PAGADO | N93: EFECTIVO | O93: Mercancia - Proveedores
A94: ='COMPRAS 2025'!$D94-TODAY() -> -188 | B94: FACTURA | C94: PET EXOTIC LTDA | D94: 45860 | E94: 45860 | F94: =MONTH('COMPRAS 2025'!$E94) -> 7 | G94: 57493134 | H94: 76134946-5 | I94: SUPERMERCADO LIDER | J94: 7084 | K94: 1346 | L94: ='COMPRAS 2025'!$J94+'COMPRAS 2025'!$K94 -> 8430 | M94: PAGADO | N94: DEBITO | O94: Mercancia - Proveedores
A95: ='COMPRAS 2025'!$D95-TODAY() -> -188 | B95: FACTURA | C95: PET EXOTIC LTDA | D95: 45860 | E95: 45860 | F95: =MONTH('COMPRAS 2025'!$E95) -> 7 | G95: 57471221 | H95: 76134946-5 | I95: SUPERMERCADO LIDER | J95: 4950 | K95: 940 | L95: ='COMPRAS 2025'!$J95+'COMPRAS 2025'!$K95 -> 5890 | M95: PAGADO | N95: DEBITO | O95: Mercancia - Proveedores
A96: ='COMPRAS 2025'!$D96-TODAY() -> -217 | B96: FACTURA | C96: PET EXOTIC LTDA | D96: 45831 | E96: 45831 | F96: =MONTH('COMPRAS 2025'!$E96) -> 6 | G96: 8828183 | H96: 773982201 | I96: MERCADO LIBRE LTD | J96: 25908 | K96: 4922 | L96: ='COMPRAS 2025'!$J96+'COMPRAS 2025'!$K96 -> 30830 | M96: PAGADO | O96: Mercancia - Proveedores
A97: ='COMPRAS 2025'!$D97-TODAY() -> -201 | B97: FACTURA | C97: PET EXOTIC LTDA | D97: 45847 | E97: 45847 | F97: =MONTH('COMPRAS 2025'!$E97) -> 7 | G97: 9036130 | H97: 773982201 | I97: MERCADO LIBRE LTD | J97: 5032 | K97: 956 | L97: ='COMPRAS 2025'!$J97+'COMPRAS 2025'!$K97 -> 5988 | M97: PAGADO | O97: Mercancia - Proveedores
A98: ='COMPRAS 2025'!$D98-TODAY() -> -201 | B98: FACTURA | C98: PET EXOTIC LTDA | D98: 45847 | E98: 45847 | F98: =MONTH('COMPRAS 2025'!$E98) -> 7 | G98: 9036131 | H98: 773982201 | I98: MERCADO LIBRE LTD | J98: 38454 | K98: 7306 | L98: ='COMPRAS 2025'!$J98+'COMPRAS 2025'!$K98 -> 45760 | M98: PAGADO | O98: Mercancia - Proveedores
A99: ='COMPRAS 2025'!$D99-TODAY() -> -156 | B99: FACTURA | C99: PET EXOTIC SPA | D99: 45892 | E99: 45862 | F99: =MONTH('COMPRAS 2025'!$E99) -> 7 | G99: 2421606 | H99: 81643200-6 | I99: COOPERATIVA AGRICOLA LECHERA STGO. | J99: 30866 | K99: 5865 | L99: ='COMPRAS 2025'!$J99+'COMPRAS 2025'!$K99 -> 36731 | M99: PAGADO | O99: Mercancia - Proveedores
A100: ='COMPRAS 2025'!$D100-TODAY() -> -156 | B100: FACTURA | C100: PET EXOTIC SPA | D100: 45892 | E100: 45862 | F100: =MONTH('COMPRAS 2025'!$E100) -> 7 | G100: 2421605 | H100: 81643200-6 | I100: COOPERATIVA AGRICOLA LECHERA STGO. | J100: 298820 | K100: 56776 | L100: ='COMPRAS 2025'!$J100+'COMPRAS 2025'!$K100 -> 355596 | M100: PAGADO | O100: Mercancia - Proveedores
A101: ='COMPRAS 2025'!$D101-TODAY() -> -181 | B101: FACTURA | C101: PET EXOTIC SPA | D101: 45867 | E101: 45867 | F101: =MONTH('COMPRAS 2025'!$E101) -> 7 | G101: 605041 | H101: 76613670-2 | I101: IMPORTADORA COMERCIALIZADORA Y DISTRIBUIDORA ROYAL CANIN CHILE LIMITADA | J101: 98440 | K101: 18704 | L101: ='COMPRAS 2025'!$J101+'COMPRAS 2025'!$K101 -> 117144 | M101: PAGADO | O101: Mercancia - Proveedores
A102: ='COMPRAS 2025'!$D102-TODAY() -> -151 | B102: FACTURA | C102: PET EXOTIC LTDA | D102: 45897 | E102: 45867 | F102: =MONTH('COMPRAS 2025'!$E102) -> 7 | G102: 405985 | H102: 76080982-9 | I102: DIPROVET DISTRIBUIDORA DE PRODUCTOS VETERINARIOS SPA | J102: 72360 | K102: 13748 | L102: ='COMPRAS 2025'!$J102+'COMPRAS 2025'!$K102 -> 86108 | M102: PAGADO | O102: Mercancia - Proveedores
A103: ='COMPRAS 2025'!$D103-TODAY() -> -151 | B103: FACTURA | C103: PET EXOTIC LTDA | D103: 45897 | E103: 45867 | F103: =MONTH('COMPRAS 2025'!$E103) -> 7 | G103: 405987 | H103: 76080982-9 | I103: DIPROVET DISTRIBUIDORA DE PRODUCTOS VETERINARIOS SPA | J103: 17990 | K103: 3418 | L103: ='COMPRAS 2025'!$J103+'COMPRAS 2025'!$K103 -> 21408 | M103: PAGADO | O103: Mercancia - Proveedores
A104: ='COMPRAS 2025'!$D104-TODAY() -> -151 | B104: FACTURA | C104: PET EXOTIC LTDA | D104: 45897 | E104: 45867 | F104: =MONTH('COMPRAS 2025'!$E104) -> 7 | G104: 405988 | H104: 76080982-9 | I104: DIPROVET DISTRIBUIDORA DE PRODUCTOS VETERINARIOS SPA | J104: 64740 | K104: 12301 | L104: ='COMPRAS 2025'!$J104+'COMPRAS 2025'!$K104 -> 77041 | M104: PAGADO | O104: Mercancia - Proveedores
A105: ='COMPRAS 2025'!$D105-TODAY() -> -145 | B105: FACTURA | C105: PET EXOTIC LTDA | D105: 45903 | E105: 45873 | F105: =MONTH('COMPRAS 2025'!$E105) -> 8 | G105: 406490 | H105: 76080982-9 | I105: DIPROVET DISTRIBUIDORA DE PRODUCTOS VETERINARIOS SPA | J105: 38980 | K105: 7406 | L105: ='COMPRAS 2025'!$J105+'COMPRAS 2025'!$K105 -> 46386 | M105: PAGADO | O105: Mercancia - Proveedores
A106: ='COMPRAS 2025'!$D106-TODAY() -> -145 | B106: FACTURA | C106: PET EXOTIC LTDA | D106: 45903 | E106: 45873 | F106: =MONTH('COMPRAS 2025'!$E106) -> 8 | G106: 406491 | H106: 76080982-9 | I106: DIPROVET DISTRIBUIDORA DE PRODUCTOS VETERINARIOS SPA | J106: 87657 | K106: 16655 | L106: ='COMPRAS 2025'!$J106+'COMPRAS 2025'!$K106 -> 104312 | M106: PAGADO | O106: Mercancia - Proveedores
A107: ='COMPRAS 2025'!$D107-TODAY() -> -145 | B107: FACTURA | C107: PET EXOTIC LTDA | D107: 45903 | E107: 45873 | F107: =MONTH('COMPRAS 2025'!$E107) -> 8 | G107: 406492 | H107: 76080982-9 | I107: DIPROVET DISTRIBUIDORA DE PRODUCTOS VETERINARIOS SPA | J107: 9490 | K107: 1803 | L107: ='COMPRAS 2025'!$J107+'COMPRAS 2025'!$K107 -> 11293 | M107: PAGADO | O107: Mercancia - Proveedores
A108: ='COMPRAS 2025'!$D108-TODAY() -> -138 | B108: FACTURA | C108: PET EXOTIC SPA | D108: 45910 | E108: 45880 | F108: =MONTH('COMPRAS 2025'!$E108) -> 8 | G108: 407483 | H108: 76080982-9 | I108: DIPROVET DISTRIBUIDORA DE PRODUCTOS VETERINARIOS SPA | J108: 114338 | K108: 21724 | L108: ='COMPRAS 2025'!$J108+'COMPRAS 2025'!$K108 -> 136062 | M108: PAGADO | O108: Mercancia - Proveedores
A109: ='COMPRAS 2025'!$D109-TODAY() -> -138 | B109: FACTURA | C109: PET EXOTIC SPA | D109: 45910 | E109: 45880 | F109: =MONTH('COMPRAS 2025'!$E109) -> 8 | G109: 407482 | H109: 76080982-9 | I109: DIPROVET DISTRIBUIDORA DE PRODUCTOS VETERINARIOS SPA | J109: 186223 | K109: 35382 | L109: ='COMPRAS 2025'!$J109+'COMPRAS 2025'!$K109 -> 221605 | M109: PAGADO | O109: Mercancia - Proveedores
A110: ='COMPRAS 2025'!$D110-TODAY() -> -137 | B110: FACTURA | C110: PET EXOTIC SPA | D110: 45911 | E110: 45881 | F110: =MONTH('COMPRAS 2025'!$E110) -> 8 | G110: 103981 | H110: 76936850-7 | I110: ANIMAL CARE - ACWS S.A | J110: 82639 | K110: 15701 | L110: ='COMPRAS 2025'!$J110+'COMPRAS 2025'!$K110 -> 98340 | M110: PAGADO | O110: Mercancia - Proveedores
A111: ='COMPRAS 2025'!$D111-TODAY() -> -129 | B111: FACTURA | C111: PET EXOTIC LTDA | D111: 45919 | E111: 45889 | F111: =MONTH('COMPRAS 2025'!$E111) -> 8 | G111: 52850 | H111: 76199127-2 | I111: COMERCIAL LEGUER S.A | J111: 131621 | K111: 25008 | L111: ='COMPRAS 2025'!$J111+'COMPRAS 2025'!$K111 -> 156629 | M111: PAGADO | O111: Mercancia - Proveedores
A112: ='COMPRAS 2025'!$D112-TODAY() -> -153 | B112: FACTURA | C112: PET EXOTIC LTDA | D112: 45895 | E112: 45895 | F112: =MONTH('COMPRAS 2025'!$E112) -> 8 | G112: 17843 | H112: 167748139 | I112: JOSE IGNACIO MORENO URRA | J112: 5883 | K112: 1118 | L112: ='COMPRAS 2025'!$J112+'COMPRAS 2025'!$K112 -> 7001 | M112: PAGADO | N112: DEBITO | O112: Mercancia - Proveedores
A113: ='COMPRAS 2025'!$D113-TODAY() -> -120 | B113: FACTURA | C113: PET EXOTIC SPA | D113: 45928 | E113: 45898 | F113: =MONTH('COMPRAS 2025'!$E113) -> 8 | G113: 2444615 | H113: 81643200-6 | I113: COOPERATIVA AGRICOLA LECHERA STGO. | J113: 73896 | K113: 14040 | L113: ='COMPRAS 2025'!$J113+'COMPRAS 2025'!$K113 -> 87936 | M113: PAGADO | O113: Mercancia - Proveedores
A114: ='COMPRAS 2025'!$D114-TODAY() -> -120 | B114: FACTURA | C114: PET EXOTIC SPA | D114: 45928 | E114: 45898 | F114: =MONTH('COMPRAS 2025'!$E114) -> 8 | G114: 2444605 | H114: 81643200-6 | I114: COOPERATIVA AGRICOLA LECHERA STGO. | J114: 94062 | K114: 17872 | L114: ='COMPRAS 2025'!$J114+'COMPRAS 2025'!$K114 -> 111934 | M114: PAGADO | O114: Mercancia - Proveedores
A115: ='COMPRAS 2025'!$D115-TODAY() -> -115 | B115: FACTURA | C115: PET EXOTIC LTDA | D115: 45933 | E115: 45903 | F115: =MONTH('COMPRAS 2025'!$E115) -> 9 | G115: 11853 | H115: 76046685-9 | I115: DATAMEDICA S.P.A | J115: 90000 | K115: 17100 | L115: ='COMPRAS 2025'!$J115+'COMPRAS 2025'!$K115 -> 107100 | M115: PAGADO | O115: Mercancia - Proveedores
A116: ='COMPRAS 2025'!$D116-TODAY() -> -108 | B116: FACTURA | C116: PET EXOTIC SPA | D116: 45940 | E116: 45910 | F116: =MONTH('COMPRAS 2025'!$E116) -> 9 | G116: 2453233 | H116: 81643200-6 | I116: COOPERATIVA AGRICOLA LECHERA STGO. | J116: 80451 | K116: 15286 | L116: ='COMPRAS 2025'!$J116+'COMPRAS 2025'!$K116 -> 95737 | M116: PAGADO | O116: Mercancia - Proveedores
A117: ='COMPRAS 2025'!$D117-TODAY() -> -108 | B117: FACTURA | C117: PET EXOTIC LTDA | D117: 45940 | E117: 45910 | F117: =MONTH('COMPRAS 2025'!$E117) -> 9 | G117: 2453253 | H117: 81643200-6 | I117: COOPERATIVA AGRICOLA LECHERA STGO. | J117: 31294 | K117: 5946 | L117: ='COMPRAS 2025'!$J117+'COMPRAS 2025'!$K117 -> 37240 | M117: PAGADO | O117: Mercancia - Proveedores
A118: ='COMPRAS 2025'!$D118-TODAY() -> -92 | B118: FACTURA | C118: PET EXOTIC SPA | D118: 45956 | E118: 45926 | F118: =MONTH('COMPRAS 2025'!$E118) -> 9 | G118: 2464103 | H118: 81643200-6 | I118: COOPERATIVA AGRICOLA LECHERA STGO. | J118: 67649 | K118: 12853 | L118: ='COMPRAS 2025'!$J118+'COMPRAS 2025'!$K118 -> 80502 | M118: PAGADO | O118: Mercancia - Proveedores
A119: ='COMPRAS 2025'!$D119-TODAY() -> -92 | B119: FACTURA | C119: PET EXOTIC SPA | D119: 45956 | E119: 45926 | F119: =MONTH('COMPRAS 2025'!$E119) -> 9 | G119: 2464116 | H119: 81643200-6 | I119: COOPERATIVA AGRICOLA LECHERA STGO. | J119: 9800 | K119: 1862 | L119: ='COMPRAS 2025'!$J119+'COMPRAS 2025'!$K119 -> 11662 | M119: PAGADO | O119: Mercancia - Proveedores
A120: ='COMPRAS 2025'!$D120-TODAY() -> -92 | B120: FACTURA | C120: PET EXOTIC SPA | D120: 45956 | E120: 45926 | F120: =MONTH('COMPRAS 2025'!$E120) -> 9 | G120: 2464106 | H120: 81643200-6 | I120: COOPERATIVA AGRICOLA LECHERA STGO. | J120: 40448 | K120: 7685 | L120: ='COMPRAS 2025'!$J120+'COMPRAS 2025'!$K120 -> 48133 | M120: PAGADO | O120: Mercancia - Proveedores
A121: ='COMPRAS 2025'!$D121-TODAY() -> -74 | B121: FACTURA | C121: PET EXOTIC LTDA | D121: 45974 | E121: 45944 | F121: =MONTH('COMPRAS 2025'!$E121) -> 10 | G121: 415842 | H121: 76080982-9 | I121: DIPROVET DISTRIBUIDORA DE PRODUCTOS VETERINARIOS SPA | J121: 23990 | K121: 4558 | L121: ='COMPRAS 2025'!$J121+'COMPRAS 2025'!$K121 -> 28548 | M121: PAGADO | O121: Mercancia - Proveedores
A122: ='COMPRAS 2025'!$D122-TODAY() -> -74 | B122: FACTURA | C122: PET EXOTIC LTDA | D122: 45974 | E122: 45944 | F122: =MONTH('COMPRAS 2025'!$E122) -> 10 | G122: 415761 | H122: 76080982-9 | I122: DIPROVET DISTRIBUIDORA DE PRODUCTOS VETERINARIOS SPA | J122: 100940 | K122: 19179 | L122: ='COMPRAS 2025'!$J122+'COMPRAS 2025'!$K122 -> 120119 | M122: PAGADO | O122: Mercancia - Proveedores
A123: ='COMPRAS 2025'!$D123-TODAY() -> -74 | B123: FACTURA | C123: PET EXOTIC LTDA | D123: 45974 | E123: 45944 | F123: =MONTH('COMPRAS 2025'!$E123) -> 10 | G123: 415843 | H123: 76080982-9 | I123: DIPROVET DISTRIBUIDORA DE PRODUCTOS VETERINARIOS SPA | J123: 70230 | K123: 13344 | L123: ='COMPRAS 2025'!$J123+'COMPRAS 2025'!$K123 -> 83574 | M123: PAGADO | O123: Mercancia - Proveedores
A124: ='COMPRAS 2025'!$D124-TODAY() -> -68 | B124: FACTURA | C124: PET EXOTIC LTDA | D124: 45980 | E124: 45950 | F124: =MONTH('COMPRAS 2025'!$E124) -> 10 | G124: 12128 | H124: 76046685-9 | I124: DATAMEDICA S.P.A | J124: 95000 | K124: 18050 | L124: ='COMPRAS 2025'!$J124+'COMPRAS 2025'!$K124 -> 113050 | M124: PAGADO | O124: Mercancia - Proveedores
A125: ='COMPRAS 2025'!$D125-TODAY() -> -95 | B125: FACTURA | C125: PET EXOTIC SPA | D125: 45953 | E125: 45953 | F125: =MONTH('COMPRAS 2025'!$E125) -> 10 | G125: 48043 | H125: 76839842-9 | I125: COMERCIALIZADORA MGASES SPA | J125: 39220 | K125: 7452 | L125: ='COMPRAS 2025'!$J125+'COMPRAS 2025'!$K125 -> 46672 | M125: PAGADO | N125: TRANSFERENCIA | O125: Mercancia - Proveedores
A126: ='COMPRAS 2025'!$D126-TODAY() -> -58 | B126: FACTURA | C126: PET EXOTIC SPA | D126: 45990 | E126: 45960 | F126: =MONTH('COMPRAS 2025'!$E126) -> 10 | G126: 106287 | H126: 76936850-7 | I126: ANIMAL CARE - ACWS S.A | J126: 123560 | K126: 23476 | L126: ='COMPRAS 2025'!$J126+'COMPRAS 2025'!$K126 -> 147036 | M126: PAGADO | O126: Mercancia - Proveedores
A127: ='COMPRAS 2025'!$D127-TODAY() -> -54 | B127: FACTURA | C127: PET EXOTIC LTDA | D127: 45994 | E127: 45964 | F127: =MONTH('COMPRAS 2025'!$E127) -> 11 | G127: 418297 | H127: 76080982-9 | I127: DIPROVET DISTRIBUIDORA DE PRODUCTOS VETERINARIOS SPA | J127: 49790 | K127: 9460 | L127: ='COMPRAS 2025'!$J127+'COMPRAS 2025'!$K127 -> 59250 | M127: PAGADO | O127: Mercancia - Proveedores
A128: ='COMPRAS 2025'!$D128-TODAY() -> -54 | B128: FACTURA | C128: PET EXOTIC SPA | D128: 45994 | E128: 45964 | F128: =MONTH('COMPRAS 2025'!$E128) -> 11 | G128: 418316 | H128: 76080982-9 | I128: DIPROVET DISTRIBUIDORA DE PRODUCTOS VETERINARIOS SPA | J128: 240995 | K128: 45789 | L128: ='COMPRAS 2025'!$J128+'COMPRAS 2025'!$K128 -> 286784 | M128: PAGADO | O128: Mercancia - Proveedores
A129: ='COMPRAS 2025'!$D129-TODAY() -> -54 | B129: FACTURA | C129: PET EXOTIC LTDA | D129: 45994 | E129: 45964 | F129: =MONTH('COMPRAS 2025'!$E129) -> 11 | G129: 418296 | H129: 76080982-9 | I129: DIPROVET DISTRIBUIDORA DE PRODUCTOS VETERINARIOS SPA | J129: 51476 | K129: 9780 | L129: ='COMPRAS 2025'!$J129+'COMPRAS 2025'!$K129 -> 61256 | M129: PAGADO | O129: Mercancia - Proveedores
A130: ='COMPRAS 2025'!$D130-TODAY() -> -46 | B130: FACTURA | C130: PET EXOTIC SPA | D130: 46002 | E130: 45972 | F130: =MONTH('COMPRAS 2025'!$E130) -> 11 | G130: 38882976 | H130: 90703000-8 | I130: NESTLE Chile S.A. | J130: 148232 | K130: 28164 | L130: ='COMPRAS 2025'!$J130+'COMPRAS 2025'!$K130 -> 176396 | M130: PAGADO | O130: Mercancia - Proveedores
A131: ='COMPRAS 2025'!$D131-TODAY() -> -80 | B131: FACTURA | C131: PET EXOTIC SPA | D131: 45968 | E131: 45968 | F131: =MONTH('COMPRAS 2025'!$E131) -> 11 | G131: 231976 | H131: 76416389-3 | I131: HALLMARK S.A. | J131: 152191 | K131: 28916 | L131: ='COMPRAS 2025'!$J131+'COMPRAS 2025'!$K131 -> 181107 | M131: PAGADO | O131: Mercancia - Proveedores
A132: ='COMPRAS 2025'!$D132-TODAY() -> -75 | B132: FACTURA | C132: PET EXOTIC SPA | D132: 45973 | E132: 45973 | F132: =MONTH('COMPRAS 2025'!$E132) -> 11 | G132: 2501515 | H132: 81643200-6 | I132: COOPERATIVA AGRICOLA LECHERA STGO. | J132: 100892 | K132: 19169 | L132: ='COMPRAS 2025'!$J132+'COMPRAS 2025'!$K132 -> 120061 | M132: PAGADO | O132: Mercancia - Proveedores
A133: ='COMPRAS 2025'!$D133-TODAY() -> -44 | B133: FACTURA | C133: PET EXOTIC LTDA | D133: 46004 | E133: 45974 | F133: =MONTH('COMPRAS 2025'!$E133) -> 11 | G133: 419977 | H133: 76080982-9 | I133: DIPROVET DISTRIBUIDORA DE PRODUCTOS VETERINARIOS SPA | J133: 101367 | K133: 19260 | L133: ='COMPRAS 2025'!$J133+'COMPRAS 2025'!$K133 -> 120627 | M133: PAGADO | O133: Mercancia - Proveedores
A134: ='COMPRAS 2025'!$D134-TODAY() -> -51 | B134: FACTURA | C134: PET EXOTIC LTDA | D134: 45997 | E134: 45967 | F134: =MONTH('COMPRAS 2025'!$E134) -> 11 | G134: 118448 | H134: 76218200-9 | I134: DYKONOS CIA LIMITADA | J134: 181400 | K134: 34466 | L134: ='COMPRAS 2025'!$J134+'COMPRAS 2025'!$K134 -> 215866 | M134: PAGADO | O134: Mercancia - Proveedores
...

Sheet BOLETAS 2025
L1: CÓDIGO: | M1: PE-LC-01
H2: Registro Boletas 2025 | L2: VERSIÓN: | M2: 1
L3: FECHA: | M3: 45750
A4: ALERTA | B4: DOCUMENTO | C4: EMPRESA | D4: FECHA EMISION | E4: N° MES | F4: N° FOLIO | G4: RUT | H4: RAZON SOCIAL | I4: MONTO TOTAL | J4: ESTADO | K4: METODO DE PAGO | L4: CENTRO DE COSTOS | M4: DESCRIPCION
A5: =D5-TODAY() -> -385 | B5: BOLETA | C5: PET EXOTIC LTDA | D5: 45663 | E5: =MONTH('BOLETAS 2025'!$D5) -> 1 | F5: 1840257 | G5: 77178050-4 | H5: COPEC | I5: 20000 | J5: PAGADO | K5: EFECTIVO | L5: Combustible
A6: =D6-TODAY() -> -381 | B6: BOLETA | C6: PET EXOTIC LTDA | D6: 45667 | E6: =MONTH('BOLETAS 2025'!$D6) -> 1 | F6: 1843124 | G6: 77178050-4 | H6: COPEC | I6: 20000 | J6: PAGADO | K6: EFECTIVO | L6: Combustible
A7: =D7-TODAY() -> -375 | B7: BOLETA | C7: PET EXOTIC LTDA | D7: 45673 | E7: =MONTH('BOLETAS 2025'!$D7) -> 1 | F7: 1846498 | G7: 77178050-4 | H7: COPEC | I7: 20000 | J7: PAGADO | K7: DEBITO | L7: Combustible
A8: =D8-TODAY() -> -369 | B8: BOLETA | C8: PET EXOTIC LTDA | D8: 45679 | E8: =MONTH('BOLETAS 2025'!$D8) -> 1 | F8: 1851121 | G8: 77178050-4 | H8: COPEC | I8: 20000 | J8: PAGADO | K8: DEBITO | L8: Combustible
A9: =D9-TODAY() -> -367 | B9: BOLETA | C9: PET EXOTIC LTDA | D9: 45681 | E9: =MONTH('BOLETAS 2025'!$D9) -> 1 | F9: 2983224 | G9: 76587994-9 | H9: COPEC | I9: 20000 | J9: PAGADO | K9: EFECTIVO | L9: Combustible
A10: =D10-TODAY() -> -362 | B10: BOLETA | C10: PET EXOTIC LTDA | D10: 45686 | E10: =MONTH('BOLETAS 2025'!$D10) -> 1 | F10: 1855115 | G10: 77178050-4 | H10: COPEC | I10: 20000 | J10: PAGADO | K10: EFECTIVO | L10: Combustible
A11: =D11-TODAY() -> -359 | B11: BOLETA | C11: PET EXOTIC LTDA | D11: 45689 | E11: =MONTH('BOLETAS 2025'!$D11) -> 2 | F11: 23752985 | G11: 76358760-6 | H11: INVERSIONES ENEX S.A | I11: 20000 | J11: PAGADO | K11: DEBITO | L11: Combustible
A12: =D12-TODAY() -> -354 | B12: BOLETA | C12: PET EXOTIC LTDA | D12: 45694 | E12: =MONTH('BOLETAS 2025'!$D12) -> 2 | F12: 461600 | G12: 77669674-9 | H12: COPEC | I12: 20000 | J12: PAGADO | K12: DEBITO | L12: Combustible
A13: =D13-TODAY() -> -352 | B13: BOLETA | C13: PET EXOTIC LTDA | D13: 45696 | E13: =MONTH('BOLETAS 2025'!$D13) -> 2 | F13: 157967860 | G13: 94625000-7 | H13: INVERSIONES ENEX S.A | I13: 20000 | J13: PAGADO | K13: EFECTIVO | L13: Combustible
A14: =D14-TODAY() -> -349 | B14: BOLETA | C14: PET EXOTIC LTDA | D14: 45699 | E14: =MONTH('BOLETAS 2025'!$D14) -> 2 | F14: 1864379 | G14: 77178050-4 | H14: COPEC | I14: 20000 | J14: PAGADO | K14: EFECTIVO | L14: Combustible
A15: =D15-TODAY() -> -347 | B15: BOLETA | C15: PET EXOTIC LTDA | D15: 45701 | E15: =MONTH('BOLETAS 2025'!$D15) -> 2 | F15: 3758597 | G15: 76567598-7 | H15: COPEC | I15: 20000 | J15: PAGADO | K15: EFECTIVO | L15: Combustible
A16: =D16-TODAY() -> -345 | B16: BOLETA | C16: PET EXOTIC LTDA | D16: 45703 | E16: =MONTH('BOLETAS 2025'!$D16) -> 2 | F16: 1867122 | G16: 77178050-4 | H16: COPEC | I16: 20000 | J16: PAGADO | K16: EFECTIVO | L16: Combustible
... A22: =D22-TODAY() -> -305 | B22: BOLETA | C22: PET EXOTIC LTDA | D22: 45743 | E22: =MONTH('BOLETAS 2025'!$D22) -> 3 | F22: 3044835 | G22: 76587994-9 | H22: COPEC | I22: 20000 | J22: PAGADO | K22: DEBITO | L22: Combustible
A23: =D23-TODAY() -> -309 | B23: BOLETA | C23: PET EXOTIC LTDA | D23: 45739 | E23: =MONTH('BOLETAS 2025'!$D23) -> 3 | I23: 20000 | J23: PAGADO | K23: DEBITO | L23: Combustible
A24: =D24-TODAY() -> -279 | B24: BOLETA | C24: PET EXOTIC SPA | D24: 45769 | E24: =MONTH('BOLETAS 2025'!$D24) -> 4 | F24: 10865913 | G24: 88192900-7 | H24: FedEx | I24: 7496 | J24: PAGADO | K24: EFECTIVO | L24: Mercancia - Proveedores
A25: =D25-TODAY() -> -264 | B25: BOLETA | C25: PET EXOTIC LTDA | D25: 45784 | E25: =MONTH('BOLETAS 2025'!$D25) -> 5 | F25: 10869319 | G25: 88192900-7 | H25: FedEx | I25: 9587 | J25: PAGADO | K25: EFECTIVO | L25: Mercancia - Proveedores
A26: =D26-TODAY() -> -252 | B26: BOLETA | C26: PET EXOTIC LTDA | D26: 45796 | E26: =MONTH('BOLETAS 2025'!$D26) -> 5 | F26: 10872384 | G26: 88192384 | H26: FedEx | I26: 9587 | J26: PAGADO | K26: EFECTIVO | L26: Mercancia - Proveedores
A27: =D27-TODAY() -> -192 | B27: BOLETA | C27: PET EXOTIC LTDA | D27: 45856 | E27: =MONTH('BOLETAS 2025'!$D27) -> 7 | F27: 10886513 | G27: 881929007 | H27: Fedex | I27: 7130 | J27: PAGADO | K27: EFECTIVO | L27: Mercancia - Proveedores
A28: =D28-TODAY() -> -385 | B28: BOLETA | C28: PET EXOTIC LTDA | D28: 45663 | E28: =MONTH('BOLETAS 2025'!$D28) -> 1 | F28: 234524478 | G28: 59113305 | H28: Farmacia del doctor SIMI | I28: 6570 | J28: PAGADO | K28: DEBITO | L28: Mercancia - Proveedores
A29: =D29-TODAY() -> -376 | B29: BOLETA | C29: PET EXOTIC LTDA | D29: 45672 | E29: =MONTH('BOLETAS 2025'!$D29) -> 1 | F29: 74708079 | G29: 968111302 | H29: FAGASE S.A | I29: 10520 | J29: PAGADO | L29: Mercancia - Proveedores
A30: =D30-TODAY() -> -373 | B30: BOLETA | C30: PET EXOTIC LTDA | D30: 45675 | E30: =MONTH('BOLETAS 2025'!$D30) -> 1 | F30: 1093884396 | H30: SUPERMERCADO LIDER | I30: 10062 | J30: PAGADO | K30: DEBITO | L30: Mercancia - Proveedores
A31: =D31-TODAY() -> -372 | B31: BOLETA | C31: PET EXOTIC LTDA | D31: 45676 | E31: =MONTH('BOLETAS 2025'!$D31) -> 1 | F31: 5373 | G31: 772790058 | H31: INVERSIONES GASTRONOMICAS CHINAM PAS SPA | I31: 10945 | J31: PAGADO | K31: DEBITO | L31: Mercancia - Proveedores
A32: =D32-TODAY() -> -370 | B32: BOLETA | C32: PET EXOTIC LTDA | D32: 45678 | E32: =MONTH('BOLETAS 2025'!$D32) -> 1 | F32: 80435442 | G32: 968111302 | H32: FAGASE S.A | I32: 5070 | J32: PAGADO | K32: CREDITO | L32: Mercancia - Proveedores
A33: =D33-TODAY() -> -370 | B33: BOLETA | C33: PET EXOTIC LTDA | D33: 45678 | E33: =MONTH('BOLETAS 2025'!$D33) -> 1 | F33: 2056 | G33: 780442174 | H33: COMERCIALIZADORA D Y E SPA | I33: 12000 | J33: PAGADO | K33: DEBITO | L33: Mercancia - Proveedores
A34: =D34-TODAY() -> -363 | B34: BOLETA | C34: PET EXOTIC LTDA | D34: 45685 | E34: =MONTH('BOLETAS 2025'!$D34) -> 1 | F34: 2093276 | G34: 761670239 | H34: HUERTO SUR | I34: 3493 | J34: PAGADO | K34: DEBITO | L34: Mercancia - Proveedores
A35: =D35-TODAY() -> -361 | B35: BOLETA | C35: PET EXOTIC LTDA | D35: 45687 | E35: =MONTH('BOLETAS 2025'!$D35) -> 1 | F35: 1163313031 | G35: 761349465 | H35: SUPERMERCADO LIDER | I35: 112257 | J35: PAGADO | K35: DEBITO | L35: Mercancia - Proveedores
A36: =D36-TODAY() -> -361 | B36: BOLETA | C36: PET EXOTIC LTDA | D36: 45687 | E36: =MONTH('BOLETAS 2025'!$D36) -> 1 | F36: 2093382 | G36: 761670239 | H36: HUERTO SUR | I36: 3290 | J36: PAGADO | K36: DEBITO | L36: Mercancia - Proveedores
A37: =D37-TODAY() -> -369 | B37: BOLETA | C37: PET EXOTIC LTDA | D37: 45679 | E37: =MONTH('BOLETAS 2025'!$D37) -> 1 | F37: 1163342542 | G37: 76134946-5 | H37: SUPERMERCADO LIDER | I37: 47624 | J37: PAGADO | K37: EFECTIVO | L37: Mercancia - Proveedores
A38: =D38-TODAY() -> -367 | B38: BOLETA | C38: PET EXOTIC LTDA | D38: 45681 | E38: =MONTH('BOLETAS 2025'!$D38) -> 1 | F38: 2985085556 | G38: 81201000K | H38: CENCOSUD RETAIL S.A | I38: 52418 | J38: PAGADO | K38: DEBITO | L38: Mercancia - Proveedores
A39: =D39-TODAY() -> -369 | B39: BOLETA | C39: PET EXOTIC LTDA | D39: 45679 | E39: =MONTH('BOLETAS 2025'!$D39) -> 1 | F39: 246458 | G39: 898072002 | H39: FARMACIAS CRUZ VERDE | I39: 7383 | J39: PAGADO | K39: DEBITO | L39: Mercancia - Proveedores
A40: =D40-TODAY() -> -359 | B40: BOLETA | C40: PET EXOTIC LTDA | D40: 45689 | E40: =MONTH('BOLETAS 2025'!$D40) -> 2 | F40: 44042 | G40: 7553843k | H40: GENOVEVA DEL CARMEN | I40: 2600 | J40: PAGADO | K40: DEBITO | L40: Mercancia - Proveedores
A41: =D41-TODAY() -> -359 | B41: BOLETA | C41: PET EXOTIC LTDA | D41: 45689 | E41: =MONTH('BOLETAS 2025'!$D41) -> 2 | I41: 5000 | J41: PAGADO | L41: Mercancia - Proveedores
A42: =D42-TODAY() -> -359 | B42: BOLETA | C42: PET EXOTIC LTDA | D42: 45689 | E42: =MONTH('BOLETAS 2025'!$D42) -> 2 | F42: 77978686 | G42: 764333101 | H42: CENCOSUD SHOPPING S.A | I42: 1650 | J42: PAGADO | K42: DEBITO | L42: Mercancia - Proveedores
A43: =D43-TODAY() -> -358 | B43: BOLETA | C43: PET EXOTIC LTDA | D43: 45690 | E43: =MONTH('BOLETAS 2025'!$D43) -> 2 | F43: 34428 | G43: 968111302 | H43: FAGASE S.A | I43: 1690 | J43: PAGADO | K43: DEBITO | L43: Mercancia - Proveedores
A44: =D44-TODAY() -> -358 | B44: BOLETA | C44: PET EXOTIC LTDA | D44: 45690 | E44: =MONTH('BOLETAS 2025'!$D44) -> 2 | F44: 34427 | G44: 96811302 | H44: FAGASE S.A | I44: 5290 | J44: PAGADO | K44: DEBITO | L44: Mercancia - Proveedores
A45: =D45-TODAY() -> -357 | B45: BOLETA | C45: PET EXOTIC LTDA | D45: 45691 | E45: =MONTH('BOLETAS 2025'!$D45) -> 2 | F45: 19667 | G45: 898072002 | H45: CRUZ VERDE | I45: 1990 | J45: PAGADO | K45: DEBITO | L45: Mercancia - Proveedores
A46: =D46-TODAY() -> -356 | B46: BOLETA | C46: PET EXOTIC LTDA | D46: 45692 | E46: =MONTH('BOLETAS 2025'!$D46) -> 2 | F46: 80439902 | G46: 968111302 | H46: FAGASE S.A | I46: 5070 | J46: PAGADO | L46: Mercancia - Proveedores
A47: =D47-TODAY() -> -356 | B47: BOLETA | C47: PET EXOTIC LTDA | D47: 45692 | E47: =MONTH('BOLETAS 2025'!$D47) -> 2 | F47: 248925761 | G47: 765686601 | H47: EASY RETAIL SA | I47: 5490 | J47: PAGADO | K47: EFECTIVO | L47: Mercancia - Proveedores
A48: =D48-TODAY() -> -356 | B48: BOLETA | C48: PET EXOTIC LTDA | D48: 45692 | E48: =MONTH('BOLETAS 2025'!$D48) -> 2 | F48: 778743787 | H48: ARANCIBIA CERRAJERO SPA | I48: 4000 | J48: PAGADO | K48: DEBITO | L48: Mercancia - Proveedores
A49: =D49-TODAY() -> -356 | B49: BOLETA | C49: PET EXOTIC LTDA | D49: 45692 | E49: =MONTH('BOLETAS 2025'!$D49) -> 2 | F49: 105045 | G49: 76645914 | H49: VIRGILIO FERNANDO POLANCO | I49: 1600 | J49: PAGADO | K49: DEBITO | L49: Mercancia - Proveedores
A50: =D50-TODAY() -> -355 | B50: BOLETA | C50: PET EXOTIC LTDA | D50: 45693 | E50: =MONTH('BOLETAS 2025'!$D50) -> 2 | F50: 311167 | G50: 159738388 | H50: PUERTO PET | I50: 12500 | J50: PAGADO | K50: DEBITO | L50: Mercancia - Proveedores
A51: =D51-TODAY() -> -355 | B51: BOLETA | C51: PET EXOTIC LTDA | D51: 45693 | E51: =MONTH('BOLETAS 2025'!$D51) -> 2 | F51: 78739 | G51: 774219161 | H51: LUCKY STAR XIE LTDA | I51: 1350 | J51: PAGADO | L51: Mercancia - Proveedores
A52: =D52-TODAY() -> -353 | B52: BOLETA | C52: PET EXOTIC LTDA | D52: 45695 | E52: =MONTH('BOLETAS 2025'!$D52) -> 2 | F52: 25470 | G52: 837595002 | H52: VICINAY HENRIQUEZ | I52: 10400 | J52: PAGADO | K52: DEBITO | L52: Mercancia - Proveedores
A53: =D53-TODAY() -> -353 | B53: BOLETA | C53: PET EXOTIC LTDA | D53: 45695 | E53: =MONTH('BOLETAS 2025'!$D53) -> 2 | F53: 59 | G53: 771489478 | H53: PUNTO MOVIL A Y M SPA | I53: 2200 | J53: PAGADO | K53: DEBITO | L53: Mercancia - Proveedores
A54: =D54-TODAY() -> -353 | B54: BOLETA | C54: PET EXOTIC LTDA | D54: 45695 | E54: =MONTH('BOLETAS 2025'!$D54) -> 2 | F54: 20381 | G54: 766378935 | H54: RAMIIREZ Y AVILES | I54: 2900 | J54: PAGADO | K54: DEBITO | L54: Mercancia - Proveedores
A55: =D55-TODAY() -> -353 | B55: BOLETA | C55: PET EXOTIC LTDA | D55: 45695 | E55: =MONTH('BOLETAS 2025'!$D55) -> 2 | F55: 566011 | G55: 96973500 | H55: VERDULERIA LOS CATUERROS | I55: 2000 | J55: PAGADO | K55: DEBITO | L55: Mercancia - Proveedores
A56: =D56-TODAY() -> -353 | B56: BOLETA | C56: PET EXOTIC LTDA | D56: 45695 | E56: =MONTH('BOLETAS 2025'!$D56) -> 2 | F56: 93215 | G56: 64230085 | H56: ISABEL BRITO | I56: 1500 | J56: PAGADO | K56: DEBITO | L56: Mercancia - Proveedores
A57: =D57-TODAY() -> -353 | B57: BOLETA | C57: PET EXOTIC LTDA | D57: 45695 | E57: =MONTH('BOLETAS 2025'!$D57) -> 2 | F57: 143587857 | G57: 690609002 | H57: MUNICIPALIDAD VALPARAISO | I57: 2100 | J57: PAGADO | K57: DEBITO | L57: Mercancia - Proveedores
A58: =D58-TODAY() -> -351 | B58: BOLETA | C58: PET EXOTIC LTDA | D58: 45697 | E58: =MONTH('BOLETAS 2025'!$D58) -> 2 | F58: 51356 | G58: 774985522 | H58: HERMANOS PINTO | I58: 40700 | J58: PAGADO | K58: DEBITO | L58: Mercancia - Proveedores
A59: =D59-TODAY() -> -351 | B59: BOLETA | C59: PET EXOTIC LTDA | D59: 45697 | E59: =MONTH('BOLETAS 2025'!$D59) -> 2 | F59: 75033 | G59: 778307677 | H59: INSPIRA KIDS SPA | I59: 39800 | J59: PAGADO | L59: Mercancia - Proveedores
A60: =D60-TODAY() -> -347 | B60: BOLETA | C60: PET EXOTIC LTDA | D60: 45701 | E60: =MONTH('BOLETAS 2025'!$D60) -> 2 | F60: 1094045156 | G60: 76134946-5 | H60: SUPERMERCADO LIDER | I60: 50226 | J60: PAGADO | K60: DEBITO | L60: Mercancia - Proveedores
A61: =D61-TODAY() -> -343 | B61: BOLETA | C61: PET EXOTIC LTDA | D61: 45705 | E61: =MONTH('BOLETAS 2025'!$D61) -> 2 | F61: 1147287292 | G61: 76134946-5 | H61: SUPERMERCADO LIDER | I61: 62826 | J61: PAGADO | K61: DEBITO | L61: Mercancia - Proveedores
A62: =D62-TODAY() -> -343 | B62: BOLETA | C62: PET EXOTIC LTDA | D62: 45705 | E62: =MONTH('BOLETAS 2025'!$D62) -> 2 | F62: 4540073 | G62: 763608689 | H62: KIOSCLUB AMERICAM | I62: 3190 | J62: PAGADO | K62: DEBITO | L62: Mercancia - Proveedores
A63: =D63-TODAY() -> -341 | B63: BOLETA | C63: PET EXOTIC LTDA | D63: 45707 | E63: =MONTH('BOLETAS 2025'!$D63) -> 2 | F63: 200964 | G63: 77874387 | H63: LOS MAGNIFICOS 2 | I63: 3300 | J63: PAGADO | K63: DEBITO | L63: Mercancia - Proveedores
A64: =D64-TODAY() -> -341 | B64: BOLETA | C64: PET EXOTIC LTDA | D64: 45707 | E64: =MONTH('BOLETAS 2025'!$D64) -> 2 | F64: 502190052 | G64: 774219161 | H64: COM E IMP LUCKY STAR XIE LTDA | I64: 4050 | J64: PAGADO | K64: DEBITO | L64: Mercancia - Proveedores
A65: =D65-TODAY() -> -341 | B65: BOLETA | C65: PET EXOTIC LTDA | D65: 45707 | E65: =MONTH('BOLETAS 2025'!$D65) -> 2 | F65: 8418033 | G65: 776481807 | H65: BEFOODS LTD | I65: 5410 | J65: PAGADO | L65: Mercancia - Proveedores
A66: =D66-TODAY() -> -341 | B66: BOLETA | C66: PET EXOTIC LTDA | D66: 45707 | E66: =MONTH('BOLETAS 2025'!$D66) -> 2 | F66: 46386719 | G66: 995543907 | H66: SABA | I66: 3300 | J66: PAGADO | K66: DEBITO | L66: Mercancia - Proveedores
A67: =D67-TODAY() -> -341 | B67: BOLETA | C67: PET EXOTIC LTDA | D67: 45707 | E67: =MONTH('BOLETAS 2025'!$D67) -> 2 | F67: 1192338255 | G67: 76134946-5 | H67: SUPERMERCADO LIDER | I67: 24540 | J67: PAGADO | K67: DEBITO | L67: Mercancia - Proveedores
A68: =D68-TODAY() -> -339 | B68: BOLETA | C68: PET EXOTIC LTDA | D68: 45709 | E68: =MONTH('BOLETAS 2025'!$D68) -> 2 | F68: 2094243 | G68: 761670239 | H68: HUERTO SUR | I68: 3353 | J68: PAGADO | K68: DEBITO | L68: Mercancia - Proveedores
A69: =D69-TODAY() -> -339 | B69: BOLETA | C69: PET EXOTIC LTDA | D69: 45709 | E69: =MONTH('BOLETAS 2025'!$D69) -> 2 | F69: 112474 | G69: 64230085 | H69: ISABEL BRITO | I69: 6500 | J69: PAGADO | K69: CREDITO | L69: Mercancia - Proveedores
A70: =D70-TODAY() -> -339 | B70: BOLETA | C70: PET EXOTIC LTDA | D70: 45709 | E70: =MONTH('BOLETAS 2025'!$D70) -> 2 | F70: 26974 | G70: 774219161 | H70: LUCKY STAR XIE | I70: 1350 | J70: PAGADO | K70: CREDITO | L70: Mercancia - Proveedores
A71: =D71-TODAY() -> -339 | B71: BOLETA | C71: PET EXOTIC LTDA | D71: 45709 | E71: =MONTH('BOLETAS 2025'!$D71) -> 2 | F71: 10733 | G71: 773790469 | H71: I MPORTACIONES TENG DA SPA | I71: 8990 | J71: PAGADO | K71: DEBITO | L71: Mercancia - Proveedores
A72: =D72-TODAY() -> -337 | B72: BOLETA | C72: PET EXOTIC LTDA | D72: 45711 | E72: =MONTH('BOLETAS 2025'!$D72) -> 2 | G72: 96811302 | H72: FAGASE S.A | I72: 3380 | J72: PAGADO | K72: CREDITO | L72: Mercancia - Proveedores
A73: =D73-TODAY() -> -337 | B73: BOLETA | C73: PET EXOTIC LTDA | D73: 45711 | E73: =MONTH('BOLETAS 2025'!$D73) -> 2 | F73: 2375163 | G73: 767200943 | H73: CKICKEN | I73: 24990 | J73: PAGADO | K73: DEBITO | L73: Mercancia - Proveedores
A74: =D74-TODAY() -> -337 | B74: BOLETA | C74: PET EXOTIC LTDA | D74: 45711 | E74: =MONTH('BOLETAS 2025'!$D74) -> 2 | F74: 2328664610 | G74: 76134946-5 | H74: SUPERMERCADO LIDER | I74: 74541 | J74: PAGADO | K74: DEBITO | L74: Mercancia - Proveedores
A75: =D75-TODAY() -> -337 | B75: BOLETA | C75: PET EXOTIC LTDA | D75: 45711 | E75: =MONTH('BOLETAS 2025'!$D75) -> 2 | F75: 204 | G75: 77527425 | H75: FADA MALL CHINO | I75: 2300 | J75: PAGADO | K75: DEBITO | L75: Mercancia - Proveedores
A76: =D76-TODAY() -> -337 | B76: BOLETA | C76: PET EXOTIC LTDA | D76: 45711 | E76: =MONTH('BOLETAS 2025'!$D76) -> 2 | F76: 76959326 | G76: 96811302 | H76: FAGASE S.A | I76: 2990 | J76: PAGADO | L76: Mercancia - Proveedores
A77: =D77-TODAY() -> -337 | B77: BOLETA | C77: PET EXOTIC LTDA | D77: 45711 | E77: =MONTH('BOLETAS 2025'!$D77) -> 2 | F77: 14011958 | G77: 764583299 | H77: CANTABRIA | I77: 3990 | J77: PAGADO | K77: CREDITO | L77: Mercancia - Proveedores
A78: =D78-TODAY() -> -334 | B78: BOLETA | C78: PET EXOTIC LTDA | D78: 45714 | E78: =MONTH('BOLETAS 2025'!$D78) -> 2 | F78: 2327216986 | G78: 76134946-5 | H78: SUPERMERCADO LIDER | I78: 30050 | J78: PAGADO | K78: DEBITO | L78: Mercancia - Proveedores
A79: =D79-TODAY() -> -334 | B79: BOLETA | C79: PET EXOTIC LTDA | D79: 45714 | E79: =MONTH('BOLETAS 2025'!$D79) -> 2 | G79: 13868624 | H79: JOSI ACUNA | I79: 4000 | J79: PAGADO | K79: CREDITO | L79: Mercancia - Proveedores
A80: =D80-TODAY() -> -334 | B80: BOLETA | C80: PET EXOTIC LTDA | D80: 45714 | E80: =MONTH('BOLETAS 2025'!$D80) -> 2 | F80: 241289328 | G80: 59111330-5 | H80: FARMACIAS DE SIMILARES CHILE SA | I80: 7200 | J80: PAGADO | K80: DEBITO | L80: Mercancia - Proveedores
A81: =D81-TODAY() -> -334 | B81: BOLETA | C81: PET EXOTIC LTDA | D81: 45714 | E81: =MONTH('BOLETAS 2025'!$D81) -> 2 | F81: 2826 | G81: 771103871 | H81: GIOIA SPA | I81: 40788 | J81: PAGADO | K81: DEBITO | L81: Mercancia - Proveedores
A82: =D82-TODAY() -> -329 | B82: BOLETA | C82: PET EXOTIC LTDA | D82: 45719 | E82: =MONTH('BOLETAS 2025'!$D82) -> 3 | F82: 188392 | G82: 778950324 | H82: FELSE | I82: 37685 | J82: PAGADO | K82: DEBITO | L82: Combustible
A83: =D83-TODAY() -> -322 | B83: BOLETA | C83: PET EXOTIC LTDA | D83: 45726 | E83: =MONTH('BOLETAS 2025'!$D83) -> 3 | G83: 777168538 | H83: MARKT | I83: 1700 | J83: PAGADO | K83: DEBITO | L83: Mercancia - Proveedores
A84: =D84-TODAY() -> -331 | B84: BOLETA | C84: PET EXOTIC LTDA | D84: 45717 | E84: =MONTH('BOLETAS 2025'!$D84) -> 3 | F84: 355254 | G84: 764647459 | H84: SADU | I84: 15980 | J84: PAGADO | K84: DEBITO | L84: Mercancia - Proveedores
A85: =D85-TODAY() -> -329 | B85: BOLETA | C85: PET EXOTIC LTDA | D85: 45719 | E85: =MONTH('BOLETAS 2025'!$D85) -> 3 | F85: 74962 | G85: 795788808 | H85: LAS VEGAS LTD | I85: 171241 | J85: PAGADO | K85: DEBITO | L85: Mercancia - Proveedores
A86: =D86-TODAY() -> -329 | B86: BOLETA | C86: PET EXOTIC LTDA | D86: 45719 | E86: =MONTH('BOLETAS 2025'!$D86) -> 3 | F86: 445658 | G86: 119159728 | H86: TEREZA PEREZ | I86: 17480 | J86: PAGADO | K86: DEBITO | L86: Mercancia - Proveedores
A87: =D87-TODAY() -> -329 | B87: BOLETA | C87: PET EXOTIC LTDA | D87: 45719 | E87: =MONTH('BOLETAS 2025'!$D87) -> 3 | F87: 188393 | G87: 778950324 | H87: FELSE | I87: 2590 | J87: PAGADO | K87: CREDITO | L87: Mercancia - Proveedores
A88: =D88-TODAY() -> -328 | B88: BOLETA | C88: PET EXOTIC LTDA | D88: 45720 | E88: =MONTH('BOLETAS 2025'!$D88) -> 3 | F88: 23531 | G88: 775230665 | H88: DONGFANG | I88: 10800 | J88: PAGADO | K88: DEBITO | L88: Mercancia - Proveedores
A89: =D89-TODAY() -> -328 | B89: BOLETA | C89: PET EXOTIC LTDA | D89: 45720 | E89: =MONTH('BOLETAS 2025'!$D89) -> 3 | F89: 10807933 | G89: 766074596 | H89: SABA | I89: 51600 | J89: PAGADO | K89: CREDITO | L89: Mercancia - Proveedores
A90: =D90-TODAY() -> -328 | B90: BOLETA | C90: PET EXOTIC LTDA | D90: 45720 | E90: =MONTH('BOLETAS 2025'!$D90) -> 3 | F90: 1114301832 | G90: 76134946-5 | H90: SUPERMERCADO LIDER | I90: 18077 | J90: PAGADO | K90: DEBITO | L90: Mercancia - Proveedores
A91: =D91-TODAY() -> -328 | B91: BOLETA | C91: PET EXOTIC LTDA | D91: 45720 | E91: =MONTH('BOLETAS 2025'!$D91) -> 3 | F91: 1581019669 | G91: 898072002 | H91: FARMACIAS CRUZ VERDE | I91: 20635 | J91: PAGADO | K91: DEBITO | L91: Mercancia - Proveedores
A92: =D92-TODAY() -> -322 | B92: BOLETA | C92: PET EXOTIC LTDA | D92: 45726 | E92: =MONTH('BOLETAS 2025'!$D92) -> 3 | F92: 4491 | G92: 777633791 | H92: DONDE LA TIA SPA | I92: 2000 | J92: PAGADO | K92: DEBITO | L92: Mercancia - Proveedores
A93: =D93-TODAY() -> -313 | B93: BOLETA | C93: PET EXOTIC LTDA | D93: 45735 | E93: =MONTH('BOLETAS 2025'!$D93) -> 3 | G93: 780442174 | H93: COMERCIALIZADORA DYE SPA | I93: 6500 | J93: PAGADO | K93: DEBITO | L93: Mercancia - Proveedores
A94: =D94-TODAY() -> -314 | B94: BOLETA | C94: PET EXOTIC LTDA | D94: 45734 | E94: =MONTH('BOLETAS 2025'!$D94) -> 3 | F94: 2095277 | G94: 761670239 | H94: HUERTO SUR | I94: 3150 | J94: PAGADO | K94: DEBITO | L94: Mercancia - Proveedores
A95: =D95-TODAY() -> -304 | B95: BOLETA | C95: PET EXOTIC LTDA | D95: 45744 | E95: =MONTH('BOLETAS 2025'!$D95) -> 3 | F95: 75334 | G95: 15009948k | H95: ENEL | I95: 22980 | J95: PAGADO | K95: DEBITO | L95: Mercancia - Proveedores
A96: =D96-TODAY() -> -296 | B96: BOLETA | C96: PET EXOTIC LTDA | D96: 45752 | E96: =MONTH('BOLETAS 2025'!$D96) -> 4 | F96: 1901246 | G96: 995200007 | H96: COPEC | I96: 20000 | J96: PAGADO | K96: CREDITO | L96: Combustible
A97: =D97-TODAY() -> -290 | B97: BOLETA | C97: PET EXOTIC LTDA | D97: 45758 | E97: =MONTH('BOLETAS 2025'!$D97) -> 4 | F97: 1905739 | G97: 995200007 | H97: COPEC | I97: 30000 | J97: PAGADO | K97: EFECTIVO | L97: Combustible
A98: =D98-TODAY() -> -283 | B98: BOLETA | C98: PET EXOTIC LTDA | D98: 45765 | E98: =MONTH('BOLETAS 2025'!$D98) -> 4 | F98: 1910122 | G98: 995200007 | H98: COPEC | I98: 20000 | J98: PAGADO | K98: DEBITO | L98: Combustible
A99: =D99-TODAY() -> -273 | B99: BOLETA | C99: PET EXOTIC LTDA | D99: 45775 | E99: =MONTH('BOLETAS 2025'!$D99) -> 4 | F99: 191736 | G99: 995200007 | H99: COPEC | I99: 20000 | J99: PAGADO | K99: EFECTIVO | L99: Combustible
A100: =D100-TODAY() -> -279 | B100: BOLETA | C100: PET EXOTIC LTDA | D100: 45769 | E100: =MONTH('BOLETAS 2025'!$D100) -> 4 | F100: 650055851 | G100: 995543907 | H100: SABA | I100: 2000 | J100: PAGADO | K100: EFECTIVO | L100: Mercancia - Proveedores
A101: =D101-TODAY() -> -300 | B101: BOLETA | C101: PET EXOTIC LTDA | D101: 45748 | E101: =MONTH('BOLETAS 2025'!$D101) -> 4 | F101: 2095933 | G101: 761670239 | H101: HUERTO SUR | I101: 2870 | J101: PAGADO | K101: DEBITO | L101: Mercancia - Proveedores
A102: =D102-TODAY() -> -286 | B102: BOLETA | C102: PET EXOTIC LTDA | D102: 45762 | E102: =MONTH('BOLETAS 2025'!$D102) -> 4 | F102: 1114307703 | G102: 76134946-5 | H102: SUPERMERCADO LIDER | I102: 7915 | J102: PAGADO | L102: Mercancia - Proveedores
A103: =D103-TODAY() -> -299 | B103: BOLETA | C103: PET EXOTIC LTDA | D103: 45749 | E103: =MONTH('BOLETAS 2025'!$D103) -> 4 | F103: 46210 | G103: 995658100 | H103: comercial C.W | I103: 16170 | J103: PAGADO | K103: DEBITO | L103: Mercancia - Proveedores
A104: =D104-TODAY() -> -293 | B104: BOLETA | C104: PET EXOTIC LTDA | D104: 45755 | E104: =MONTH('BOLETAS 2025'!$D104) -> 4 | F104: 640931 | G104: 76271468K | H104: PRESSBURG | I104: 29990 | J104: PAGADO | K104: DEBITO | L104: Mercancia - Proveedores
A105: =D105-TODAY() -> -298 | B105: BOLETA | C105: PET EXOTIC LTDA | D105: 45750 | E105: =MONTH('BOLETAS 2025'!$D105) -> 4 | F105: 10791 | G105: 771479987 | H105: INV GIORGIO GRANDI | I105: 3300 | J105: PAGADO | K105: DEBITO | L105: Mercancia - Proveedores
...

Sheet PROVEEDORES CREDITO
F2: PROVEEDORES CREDITO
A4: ESTADO | B4: PROVEEDOR | C4: RUT | D4: RAZON SOCIAL | E4: MONTO CREDITO | F4: MONTO UTILIZADO | G4: MONTO DISPONIBLE | H4: DESCRIPCION | I4: COMENTARIOS
D5: PROVEEDORES | E5: - | F5: -
A6: PENDIENTE | B6: CALS | C6: 81643200-6 | D6: COOPERATIVA AGRICOLA LECHERA STGO. | E6: 0 | F6: =SUMIFS('COMPRAS 2025'!$L:$L,'COMPRAS 2025'!$M:$M,'PROVEEDORES CREDITO'!A6,'COMPRAS 2025'!$I:$I,'PROVEEDORES CREDITO'!D6) -> 0 | G6: =E6-F6 -> 0 | H6: $1.000.000 (30 DIAS) LTDA / $1.000.000 (30 DIAS) SPA | I6: NO HAY CREDITO / SOLO CONTADO
A7: PENDIENTE | B7: EQUIVET | C7: 76533504-3 | D7: CONSULTORES Y SERVICIOS INFORMATICOS SRT SPA | E7: 1000000 | F7: =SUMIFS('COMPRAS 2025'!$L:$L,'COMPRAS 2025'!$M:$M,'PROVEEDORES CREDITO'!A7,'COMPRAS 2025'!$I:$I,'PROVEEDORES CREDITO'!D7) -> 0 | G7: =E7-F7 -> 1000000 | H7: $1.000.000 (60 DIAS) SPA / LTDA
A8: PENDIENTE | B8: ANIMAL CARE | C8: 76936850-7 | D8: ANIMAL CARE - ACWS S.A | E8: 1000000 | F8: =SUMIFS('COMPRAS 2025'!$L:$L,'COMPRAS 2025'!$M:$M,'PROVEEDORES CREDITO'!A8,'COMPRAS 2025'!$I:$I,'PROVEEDORES CREDITO'!D8) -> 0 | G8: =E8-F8 -> 1000000 | H8: $1.000.000 (30 DIAS) SPA | I8: PENDIENTE AGREGAR LTDA
A9: PENDIENTE | B9: P&P | C9: 76501918-4 | D9: POBLETE Y POBLETE LIMITADA | E9: 1000000 | F9: =SUMIFS('COMPRAS 2025'!$L:$L,'COMPRAS 2025'!$M:$M,'PROVEEDORES CREDITO'!A9,'COMPRAS 2025'!$I:$I,'PROVEEDORES CREDITO'!D9) -> 0 | G9: =E9-F9 -> 1000000 | H9: $1.000.000 (30 DIAS) SPA | I9: PENDIENTE AGREGAR LTDA
A10: PENDIENTE | B10: DIPROVET | C10: 76080982-9 | D10: DIPROVET DISTRIBUIDORA DE PRODUCTOS VETERINARIOS SPA | E10: 1500000 | F10: =SUMIFS('COMPRAS 2025'!$L:$L,'COMPRAS 2025'!$M:$M,'PROVEEDORES CREDITO'!A10,'COMPRAS 2025'!$I:$I,'PROVEEDORES CREDITO'!D10) -> 0 | G10: =E10-F10 -> 1500000 | H10: $1.500.000 (30 DIAS) LTDA
A11: PENDIENTE | B11: LEGUER | C11: 76199127-2 | D11: COMERCIAL LEGUER S.A | E11: 3000000 | F11: =SUMIFS('COMPRAS 2025'!$L:$L,'COMPRAS 2025'!$M:$M,'PROVEEDORES CREDITO'!A11,'COMPRAS 2025'!$I:$I,'PROVEEDORES CREDITO'!D11) -> 0 | G11: =E11-F11 -> 3000000 | H11: $3.000.000 (30 DIAS) LTDA
A12: PENDIENTE | B12: DYKONOS | C12: 76218200-9 | D12: DYKONOS CIA LIMITADA | E12: 500000 | F12: =SUMIFS('COMPRAS 2025'!$L:$L,'COMPRAS 2025'!$M:$M,'PROVEEDORES CREDITO'!A12,'COMPRAS 2025'!$I:$I,'PROVEEDORES CREDITO'!D12) -> 0 | G12: =E12-F12 -> 500000 | H12: $500.000 (30 DIAS) LTDA
A13: PENDIENTE | B13: CLINICAL MARKET | C13: 76111113-2 | D13: CLINICAL MARKET S.A. | E13: 1000000 | F13: =SUMIFS('COMPRAS 2025'!$L:$L,'COMPRAS 2025'!$M:$M,'PROVEEDORES CREDITO'!A13,'COMPRAS 2025'!$I:$I,'PROVEEDORES CREDITO'!D13) -> 0 | G13: =E13-F13 -> 1000000 | H13: $1.000.000 (15 DIAS) LTDA
A14: PENDIENTE | E14: 0 | F14: =SUMIFS('COMPRAS 2025'!$L:$L,'COMPRAS 2025'!$M:$M,'PROVEEDORES CREDITO'!A14,'COMPRAS 2025'!$I:$I,'PROVEEDORES CREDITO'!D14) -> 0 | G14: =E14-F14 -> 0
A15: PENDIENTE | E15: 0 | F15: =SUMIFS('COMPRAS 2025'!$L:$L,'COMPRAS 2025'!$M:$M,'PROVEEDORES CREDITO'!A15,'COMPRAS 2025'!$I:$I,'PROVEEDORES CREDITO'!D15) -> 0 | G15: =E15-F15 -> 0
A16: PENDIENTE | E16: 0 | F16: =SUMIFS('COMPRAS 2025'!$L:$L,'COMPRAS 2025'!$M:$M,'PROVEEDORES CREDITO'!A16,'COMPRAS 2025'!$I:$I,'PROVEEDORES CREDITO'!D16) -> 0 | G16: =E16-F16 -> 0
D17: TOTALES | E17: =SUM(E5:E16) -> 9000000 | F17: =SUM(F5:F16) -> 0 | G17: =SUM(G5:G16) -> 9000000

Sheet LISTA PROVEEDORES
A1: 77147998-7 | B1: INVERSIONES GIORGIO JULIAN GRANDI CORRO EIRL
A2: 77034255- 4 | B2: QUINTAVET SPA
A3: 76936850-7 | B3: ANIMAL CARE - ACWS S.A
A4: 76501918-4 | B4: POBLETE Y POBLETE LIMITADA
A5: 76839842-9 | B5: COMERCIALIZADORA MGASES SPA
A6: 81643200-6 | B6: COOPERATIVA AGRICOLA LECHERA STGO.
A7: 76080982-9 | B7: DIPROVET DISTRIBUIDORA DE PRODUCTOS VETERINARIOS SPA
A8: 76979850-1 | B8: FABRICA DE BANDEJAS LIMITADA
A9: 11635852-2 | B9: PAOLA DEBORAH STACK LARA
A10: 76157270-9 | B10: SOCIEDAD COMERCIAL AQUAMUNDO LIMITADA
A11: - | B11: CANVA
A12: 96806980-2 | B12: ENTEL PCS TELECOMUNICACIONES SA
... A43: 76134946-5 | B43: SUPERMERCADO LIDER

Sheet DATOS
A1: Comisiones
A2: Mercancia - Proveedores
A3: Remuneraciones
A4: Honorarios Profesionales
A5: Servicios Contables
A6: Publicidad y Marketing
A7: Arriendo y Gastos Comunes
A8: Servicio Electricidad
A9: Servicio Agua
A10: Servicio Telefonía
A11: Servicio Internet
A12: Gastos de Oficina
... A23: Combustible
